riki_usermanager/User.py
riki_usermanager/UserManager.py
riki_usermanager/__init__.py
tests/__init__.py
tests/test_user.py
tests/test_user_manager.py
Riki_User_Manager-1.0.1.dist-info/LICENSE
Riki_User_Manager-1.0.1.dist-info/METADATA
Riki_User_Manager-1.0.1.dist-info/WHEEL
Riki_User_Manager-1.0.1.dist-info/top_level.txt
Riki_User_Manager-1.0.1.dist-info/RECORD
