Metadata-Version: 2.1
Name: Riki-User-Manager
Version: 1.0.1
Summary: User Manager utilities for the Riki
Home-page: UNKNOWN
Author: Sierra OBryan
Author-email: obryans2@nku.edu
License: UNKNOWN
Platform: UNKNOWN
